{
  "users": [
    {
      "id": 1,
      "login": "guest",
      "password": "guest"
    },
    {
      "id": 2,
      "login": "dima",
      "password": "martynov"
    },
    {
      "id": 3,
      "login": "Js",
      "password": "login"
    }
  ],
  "data": [
    {
      "id": 1,
      "limitCcal": 4000,
      "desiredWeight": 90,
      "eatingList": [
        [
          "17.8.2024",
          [
            "06:55",
            "08:27",
            "12:55",
            "19:27"
          ],
          [
            "756",
            "571",
            "847",
            "428"
          ],
          [
            "Завтрак",
            "Обед",
            "Полдник",
            "Ужин"
          ]
        ],
        [
          "16.8.2024",
          [
            "09:08",
            "12:25",
            "17:25",
            "19:51"
          ],
          [
            "829",
            "822",
            "214",
            "822"
          ],
          [
            "Завтрак",
            "Обед",
            "Полдник",
            "Ужин"
          ]
        ],
        [
          "15.8.2024",
          [
            "12:25",
            "15:54",
            "19:55"
          ],
          [
            "930",
            "503",
            "817"
          ],
          [
            "Завтрак",
            "Обед",
            "Ужин"
          ]
        ]
      ],
      "weightList": [
        [
          "17.8.2024",
          "79"
        ],
        [
          "22.8.2024",
          "78.5"
        ],
        [
          "21.8.2024",
          "78.8"
        ],
        [
          "20.8.2024",
          "79.2"
        ],
        [
          "19.8.2024",
          "80.2"
        ],
        [
          "18.8.2024",
          "81.5"
        ],
        [
          "17.8.2024",
          "80.1"
        ],
        [
          "16.8.2024",
          "79.6"
        ],
        [
          "15.8.2024",
          "79.2"
        ]
      ]
    },
    {
      "id": 2,
      "limitCcal": 2975,
      "desiredWeight": 80,
      "eatingList": [
        [
          "29.1.2025",
          [
            "07:07",
            "07:22"
          ],
          [
            954,
            184
          ],
          [
            "Торг 367",
            "Кекс 43"
          ]
        ],
        [
          "28.1.2025",
          [
            "05:44",
            "16:10",
            "16:12",
            "22:49",
            "22:51"
          ],
          [
            982,
            672,
            317,
            672,
            332
          ],
          [
            "Торт 378",
            "Котлеты порошино",
            "Пюре 374",
            "Котлеты порошино",
            "Рис 287"
          ]
        ],
        [
          "27.1.2025",
          [
            "04:21",
            "04:23",
            "16:08",
            "16:09",
            "22:56",
            "22:57"
          ],
          [
            277,
            736,
            672,
            285,
            672,
            333
          ],
          [
            "Печенье 66",
            "Кексы 172",
            "Котл порошино",
            "Пюре 336",
            "Котл порошино",
            "Пюре 392"
          ]
        ],
        [
          "26.1.2025",
          [
            "07:08",
            "13:24",
            "13:26",
            "22:54",
            "22:55",
            "22:56"
          ],
          [
            993,
            672,
            313,
            336,
            384,
            277
          ],
          [
            "Печенье 236",
            "Котлеты порошино",
            "Пюре 369",
            "Котл",
            "Бананы 427",
            "Пюре 326"
          ]
        ],
        [
          "25.1.2025",
          [
            "04:38",
            "13:07",
            "13:07",
            "13:09",
            "21:38",
            "21:40",
            "21:40",
            "21:42"
          ],
          [
            972,
            236,
            336,
            363,
            417,
            180,
            336,
            135
          ],
          [
            "Печенье 231",
            "Пюре 279",
            "Котлета порогино",
            "Кексы",
            "Сыр",
            "Бананы 200",
            "Котл",
            "Пюре 159"
          ]
        ],
        [
          "24.1.2025",
          [
            "04:48",
            "15:21",
            "15:22",
            "15:24",
            "21:51",
            "21:54"
          ],
          [
            1023,
            312,
            336,
            306,
            672,
            328
          ],
          [
            "Печенье 243",
            "Бананы 347",
            "Кото",
            "Пюре 360",
            "Котлеты порошино",
            "Пюре 386"
          ]
        ],
        [
          "23.1.2025",
          [
            "07:40",
            "07:51",
            "15:55",
            "15:57",
            "21:06",
            "21:09",
            "21:10"
          ],
          [
            900,
            184,
            672,
            219,
            672,
            278,
            51
          ],
          [
            "Печеное 214",
            "Кекс 43",
            "Котлеты пороги но 2",
            "Пюре 258",
            "Котлеты пороги но 2",
            "Бананы 309",
            "Пюре 60"
          ]
        ],
        [
          "22.1.2025",
          [
            "09:32",
            "16:01",
            "16:02",
            "21:58",
            "21:59",
            "22:00",
            "22:05",
            "22:06"
          ],
          [
            1031,
            411,
            533,
            499,
            176,
            140,
            25,
            170
          ],
          [
            "Печенье 245",
            "Колбаса 242",
            "Рожки 476",
            "Колбаса 294",
            "Рожки 158",
            "Печенье пятерочка 35",
            "Соус 31",
            "Майонез 28"
          ]
        ],
        [
          "21.1.2025",
          [
            "05:04",
            "05:17",
            "16:02",
            "16:15",
            "16:16",
            "22:01",
            "22:02"
          ],
          [
            968,
            60,
            312,
            525,
            128,
            447,
            535
          ],
          [
            "Печенье 242",
            "Печенте 15",
            "Бананы 347",
            "Сыр",
            "Печенте 32",
            "Колбаса 263",
            "Рожки 478"
          ]
        ],
        [
          "20.1.2025",
          [
            "08:47",
            "20:39",
            "20:40",
            "23:27",
            "23:27",
            "23:28"
          ],
          [
            992,
            684,
            228,
            441,
            441,
            91
          ],
          [
            "Печенте 248",
            "Блины",
            "Сырники",
            "Карт",
            "Карт",
            "Совс"
          ]
        ],
        [
          "19.1.2025",
          [
            "06:22",
            "16:07",
            "16:08",
            "22:03",
            "22:06"
          ],
          [
            992,
            377,
            671,
            680,
            260
          ],
          [
            "Печенте 248",
            "Запеканка",
            "Блинчики",
            "Колбаса",
            "Печенте 65"
          ]
        ],
        [
          "18.1.2025",
          [
            "13:16",
            "13:16",
            "13:17",
            "23:31"
          ],
          [
            249,
            971,
            485,
            1268
          ],
          [
            "Колбаса 140",
            "Слаеоны 8",
            "Слаеоны 4",
            "Печенте 317"
          ]
        ],
        [
          "17.1.2025",
          [
            "15:46",
            "15:46",
            "15:48",
            "22:00",
            "22:02"
          ],
          [
            337,
            971,
            534,
            367,
            767
          ],
          [
            "Рожки 301",
            "Слаеоны 8",
            "Колбаса 300",
            "Рожки 328",
            "Колбаса 431"
          ]
        ],
        [
          "16.1.2025",
          [
            "15:53",
            "16:01",
            "16:03",
            "19:42",
            "19:46"
          ],
          [
            971,
            493,
            501,
            493,
            514
          ],
          [
            "Слаеоны 8",
            "Рожки 441",
            "Колбаса 282",
            "441 рожки",
            "Колбаса 289"
          ]
        ],
        [
          "15.1.2025",
          [
            "04:24",
            "15:25",
            "15:26",
            "21:04",
            "21:11"
          ],
          [
            971,
            633,
            398,
            520,
            455
          ],
          [
            "Слаеоны 8",
            "Колбаса Виола 264",
            "Рожки 356",
            "Рожки 465",
            "Колбаса 256"
          ]
        ],
        [
          "14.1.2025",
          [
            "15:32",
            "15:32",
            "15:34",
            "21:56",
            "21:58"
          ],
          [
            389,
            971,
            597,
            477,
            539
          ],
          [
            "Рожки 348",
            "Слаконы 8",
            "Колбаса Виола 249",
            "Рожки 426",
            "Колбаса 302"
          ]
        ],
        [
          "13.1.2025",
          [
            "00:00",
            "14:05",
            "14:19",
            "21:18",
            "21:23"
          ],
          [
            971,
            576,
            392,
            574,
            448
          ],
          [
            "Слаконы 8",
            "Колбаса 324",
            "Рожки 350",
            "Колбаса 323",
            "Рожки 400"
          ]
        ],
        [
          "12.1.2025",
          [
            "00:01",
            "05:45",
            "05:45",
            "14:38",
            "14:42"
          ],
          [
            "971",
            "485",
            "409",
            "485",
            "623"
          ],
          [
            "Слаконы 8",
            "Слаконы 4",
            "Колбаса 230",
            "Слаконы 4",
            "Колбаса 350"
          ]
        ],
        [
          "11.1.2025",
          [
            "17:56",
            "17:56",
            "17:57",
            "17:57",
            "17:57"
          ],
          [
            "64",
            "971",
            "971",
            "363",
            "600"
          ],
          [
            "Слакон 19",
            "Слаконы 8",
            "Слаконы 8",
            "Слаконы 3",
            "Колбаса 337"
          ]
        ],
        [
          "0",
          [],
          [],
          []
        ]
      ],
      "weightList": [
        [
          "12.1.2025",
          80
        ],
        [
          "0",
          [],
          []
        ]
      ]
    },
    {
      "id": 3,
      "limitCcal": 1500,
      "desiredWeight": 90,
      "eatingList": [
        [
          "12.1.2025",
          [
            "23:08"
          ],
          [
            150
          ],
          [
            "G"
          ]
        ],
        [
          "0",
          [],
          [],
          []
        ]
      ],
      "weightList": [
        [
          "12.1.2025",
          97
        ],
        [
          "0",
          0
        ]
      ]
    }
  ]
}